pymoof/__init__.py
pymoof/clients/__init__.py
pymoof/clients/sx3.py
pymoof/profiles/__init__.py
pymoof/profiles/sx3.py
pymoof/tools/discover_bike.py
pymoof/tools/retrieve_encryption_key.py
pymoof/util/__init__.py
pymoof/util/bleak_utils.py
pymoof-0.0.6.dist-info/LICENSE
pymoof-0.0.6.dist-info/WHEEL
pymoof-0.0.6.dist-info/METADATA
pymoof-0.0.6.dist-info/RECORD
