Metadata-Version: 2.1
Name: pymoof
Version: 0.0.6
Summary: Connect to your Vanomof S3/X3 bike
Home-page: https://github.com/quantsini/pymoof
License: MIT
Author: Henri Bai
Author-email: quantsini@gmail.com
Requires-Python: >=3.7,<4.0
Classifier: License :: OSI Approved :: MIT License
Classifier: Operating System :: OS Independent
Classifier: Programming Language :: Python :: 3
Classifier: Programming Language :: Python :: 3.10
Classifier: Programming Language :: Python :: 3.7
Classifier: Programming Language :: Python :: 3.8
Classifier: Programming Language :: Python :: 3.9
Requires-Dist: bleak (>=0.14.2,<0.15.0)
Requires-Dist: cryptography (>=36.0.1,<37.0.0)
Requires-Dist: requests (>=2.27.1,<3.0.0)
Project-URL: Repository, https://github.com/quantsini/pymoof
